tja-0.5.0.dist-info/METADATA
tja-0.5.0.dist-info/WHEEL
tja-0.5.0.dist-info/licenses/LICENSE
tja/__init__.py
tja/__init__.pyi
tja/py.typed
tja/tja.pypy311-pp73-x86_64-linux-gnu.so
tja-0.5.0.dist-info/RECORD
