Metadata-Version: 2.4
Name: tja
Version: 0.5.0
Classifier: Programming Language :: Rust
Classifier: Programming Language :: Python :: Implementation :: CPython
Classifier: Programming Language :: Python :: Implementation :: PyPy
License-File: LICENSE
Summary: TJA file parser written in Rust, working in Rust, Python, and WebAssembly.
Home-Page: https://github.com/JacobLinCool/tja-rs
Requires-Python: >=3.8
